Clean_up_gcs_bucket/__init__.py
Clean_up_gcs_bucket/main.py
Clean_up_gcs_bucket-0.2.dist-info/METADATA
Clean_up_gcs_bucket-0.2.dist-info/WHEEL
Clean_up_gcs_bucket-0.2.dist-info/entry_points.txt
Clean_up_gcs_bucket-0.2.dist-info/top_level.txt
Clean_up_gcs_bucket-0.2.dist-info/RECORD
