Metadata-Version: 2.1
Name: Clean_up_gcs_bucket
Version: 0.2
